rlgridworld/__init__.py
rlgridworld/gridenv.py
rlgridworld-0.1004.dist-info/LICENSE
rlgridworld-0.1004.dist-info/METADATA
rlgridworld-0.1004.dist-info/WHEEL
rlgridworld-0.1004.dist-info/top_level.txt
rlgridworld-0.1004.dist-info/RECORD
