Metadata-Version: 2.1
Name: rlgridworld
Version: 0.1004
Summary: This is a simple yet efficient, highly customizable grid-world implementation to run reinforcement learning algorithms.
Home-page: https://github.com/Mohan-Zhang-u/rlgridworld
Author: Mohan Zhang
Author-email: mohan.zhang.mz@gmail.com
Classifier: Programming Language :: Python :: 3
Classifier: License :: OSI Approved :: MIT License
Classifier: Operating System :: OS Independent
License-File: LICENSE
Requires-Dist: gym (>=0.26.2)
Requires-Dist: numpy (>=1.24.1)
Requires-Dist: matplotlib (>=3.6.2)
Requires-Dist: opencv-python (>=4.7.0.72)
